README.md
floating.py
setup.py
floating.egg-info/PKG-INFO
floating.egg-info/SOURCES.txt
floating.egg-info/dependency_links.txt
floating.egg-info/top_level.txt