Metadata-Version: 2.1
Name: floating
Version: 0.0.1
Summary: Calculates floating precision
Home-page: https://github.com/mreiche/python-floating
Author: Mike Reiche
